kickstart/__init__.py
kickstart/application.py
kickstart/blueprint.py
kickstart/hatcher.py
kickstart/project.py
kickstart/config/__init__.py
kickstart/config/settings.json
kickstart/templates/__init__.py
kickstart/templates/app.tmpl
kickstart/templates/base.tmpl
kickstart/templates/bp_init.tmpl
kickstart/templates/config.tmpl
kickstart/templates/index.tmpl
kickstart/templates/models.tmpl
kickstart/templates/readme.tmpl
kickstart/templates/routes.tmpl
kickstart/templates/run.tmpl
flask_kickstart-0.3.dist-info/LICENSE
flask_kickstart-0.3.dist-info/METADATA
flask_kickstart-0.3.dist-info/WHEEL
flask_kickstart-0.3.dist-info/entry_points.txt
flask_kickstart-0.3.dist-info/top_level.txt
flask_kickstart-0.3.dist-info/RECORD
