Metadata-Version: 2.1
Name: flask-kickstart
Version: 0.3
Summary: Flask application scaffolding tool
Author-email: Harikumar G <hgokulam@yahoo.com>
Maintainer-email: Harikumar G <hgokulam@yahoo.com>
Project-URL: Homepage, https://hari-yahoo.github.io/flask-kickstart/
Project-URL: Repository, https://github.com/hari-yahoo/flask-kickstart.git
Project-URL: Issues, https://github.com/hari-yahoo/flask-kickstart/issues
Keywords: flask,blueprint,sqlite,scaffold,generate,webdevelopment
Classifier: Development Status :: 3 - Alpha
Classifier: Intended Audience :: Developers
Classifier: Topic :: Software Development :: Code Generators
Classifier: License :: OSI Approved :: MIT License
Classifier: Programming Language :: Python :: 3
Classifier: Programming Language :: Python :: 3.8
Classifier: Programming Language :: Python :: 3.9
Classifier: Programming Language :: Python :: 3.10
Classifier: Programming Language :: Python :: 3.11
Classifier: Programming Language :: Python :: 3.12
Classifier: Programming Language :: Python :: 3 :: Only
Requires-Python: >=3.8
License-File: LICENSE
Requires-Dist: jinja2
